pyrox/__init__.py
pyrox/constants.py
pyrox/core.py
pyrox/errors.py
pyrox/helpers.py
pyrox_client-0.2.3.dist-info/METADATA
pyrox_client-0.2.3.dist-info/WHEEL
pyrox_client-0.2.3.dist-info/RECORD
