Metadata-Version: 2.4
Name: pyrox-client
Version: 0.2.3
Summary: HYROX race data client – retrieve full race results via Python
Project-URL: Homepage, https://github.com/vmatei2/pyrox-client
Project-URL: Issues, https://github.com/vmatei2/pyrox-client/issues
Author: Vlad Matei
Classifier: License :: OSI Approved :: MIT License
Classifier: Operating System :: OS Independent
Classifier: Programming Language :: Python :: 3.12
Requires-Python: >=3.12
Requires-Dist: fastparquet>=2024.5.0
Requires-Dist: fsspec>=2024.2.0
Requires-Dist: httpx>=0.28.1
Requires-Dist: pandas>=2.3.3
Requires-Dist: platformdirs>=4.2.0
Requires-Dist: pyarrow>=22.0.0
Requires-Dist: s3fs>=2024.2.0
Requires-Dist: statsmodels>=0.14.6
Requires-Dist: twine>=6.2.0
